CHANGELOG.md
README.md
mitol/__init__.py
mitol/geoip/__init__.py
mitol/geoip/admin.py
mitol/geoip/api.py
mitol/geoip/apps.py
mitol/geoip/factories.py
mitol/geoip/models.py
mitol/geoip/py.typed
mitol/geoip/management/__init__.py
mitol/geoip/management/commands/create_private_maxmind_data.py
mitol/geoip/management/commands/import_maxmind_data.py
mitol/geoip/migrations/0001_add_geoip_tables.py
mitol/geoip/migrations/0002_rename_maxmind_tables_to_geoip.py
mitol/geoip/migrations/__init__.py
mitol_django_geoip-2025.3.17.dist-info/METADATA
mitol_django_geoip-2025.3.17.dist-info/WHEEL
mitol_django_geoip-2025.3.17.dist-info/RECORD
