Metadata-Version: 2.4
Name: mitol-django-geoip
Version: 2025.3.17
Summary: Django application to handle IP-based geolocation
License-Expression: BSD-3-Clause
Requires-Python: >=3.10
Requires-Dist: django-stubs>=1.13.1
Requires-Dist: django>=3.0
Requires-Dist: factory-boy~=3.2
Requires-Dist: faker>=4.17.1
Requires-Dist: mitol-django-common
